platform_utils/__init__.py
platform_utils/_winpaths.py
platform_utils/blackhole.py
platform_utils/clipboard.py
platform_utils/idle.py
platform_utils/paths.py
platform_utils/process.py
platform_utils/shell_integration/__init__.py
platform_utils/shell_integration/windows.py
platform_utils-1.6.2.dist-info/METADATA
platform_utils-1.6.2.dist-info/WHEEL
platform_utils-1.6.2.dist-info/licenses/LICENSE
platform_utils-1.6.2.dist-info/RECORD
