Metadata-Version: 2.4
Name: platform_utils
Version: 1.6.2
Summary: Cross-platform utilities for accomplishing some tasks that the stdlib isn't equipped to provide
Project-URL: Homepage, https://github.com/q-continuum/platform_utils
Project-URL: Issues, https://github.com/q-continuum/platform_utils/issues
Author-email: Christopher Toth <q@q-continuum.net>
License: Copyright (c) 2019 Christopher Toth
License-File: LICENSE
Classifier: Development Status :: 5 - Production/Stable
Classifier: Intended Audience :: Developers
Classifier: License :: OSI Approved :: MIT License
Classifier: Programming Language :: Python :: 3
Classifier: Programming Language :: Python :: 3.7
Classifier: Programming Language :: Python :: 3.8
Classifier: Programming Language :: Python :: 3.9
Classifier: Programming Language :: Python :: 3.10
Classifier: Programming Language :: Python :: 3.11
Classifier: Programming Language :: Python :: 3.12
Classifier: Topic :: Software Development :: Libraries
Requires-Python: >=3.7
Requires-Dist: platformdirs
Requires-Dist: pywin32; sys_platform == 'win32'
Provides-Extra: dev
Requires-Dist: pyright>=1.1.0; extra == 'dev'
